joox_web_crawler/CurlLib.py
joox_web_crawler/JooxWeb.py
joox_web_crawler/__init__.py
joox_web_crawler-0.0.9.dist-info/METADATA
joox_web_crawler-0.0.9.dist-info/RECORD
joox_web_crawler-0.0.9.dist-info/WHEEL
joox_web_crawler-0.0.9.dist-info/top_level.txt
