Metadata-Version: 2.1
Name: joox-web-crawler
Version: 0.0.9
Summary: a simple joox web crawler
Home-page: UNKNOWN
Author: Luk Chun Pong
Author-email: cpluk3@gmail.com
License: UNKNOWN
Platform: UNKNOWN
Classifier: Programming Language :: Python :: 3
Classifier: License :: OSI Approved :: MIT License
Classifier: Operating System :: OS Independent
Requires-Dist: bs4
